lisan/__init__.py
lisan/admin.py
lisan/apps.py
lisan/metaclasses.py
lisan/middleware.py
lisan/mixins.py
lisan/serializers.py
lisan/translation_services.py
lisan/utils.py
lisan-0.2.0.dist-info/licenses/LICENSE
tests/__init__.py
tests/google_translate_service.py
tests/models.py
tests/settings.py
tests/test_admin.py
tests/test_metaclasses.py
tests/test_middleware.py
tests/test_mixins.py
tests/test_serializers.py
tests/test_utils.py
lisan-0.2.0.dist-info/METADATA
lisan-0.2.0.dist-info/WHEEL
lisan-0.2.0.dist-info/top_level.txt
lisan-0.2.0.dist-info/RECORD
